agentshield_cli/__init__.py
agentshield_cli/main.py
agentshield_sdk/__init__.py
agentshield_sdk/client.py
agentshield_sdk-0.2.1.dist-info/METADATA
agentshield_sdk-0.2.1.dist-info/WHEEL
agentshield_sdk-0.2.1.dist-info/entry_points.txt
agentshield_sdk-0.2.1.dist-info/top_level.txt
agentshield_sdk-0.2.1.dist-info/RECORD
