Metadata-Version: 2.4
Name: agentshield-sdk
Version: 0.2.1
Summary: Python SDK for the AgentShield API - Runtime security for agentic AI applications.
Author-email: AgentShield Admin <hello@sanjayck.com>
Classifier: Development Status :: 3 - Alpha
Classifier: Intended Audience :: Developers
Classifier: Topic :: Security
Classifier: Topic :: Software Development :: Libraries :: Python Modules
Classifier: Operating System :: OS Independent
Classifier: Programming Language :: Python :: 3
Classifier: Programming Language :: Python :: 3.8
Classifier: Programming Language :: Python :: 3.9
Classifier: Programming Language :: Python :: 3.10
Classifier: Programming Language :: Python :: 3.11
Classifier: Programming Language :: Python :: 3.12
Requires-Python: >=3.8
Requires-Dist: httpx>=0.20.0
Requires-Dist: pydantic>=2.0
Requires-Dist: click>=8.0
